zero_python_sdk/__init__.py
zero_python_sdk/zero.py
zero_python_sdk-0.2.1.dist-info/LICENSE
zero_python_sdk-0.2.1.dist-info/METADATA
zero_python_sdk-0.2.1.dist-info/WHEEL
zero_python_sdk-0.2.1.dist-info/RECORD
